hdf5tools/__init__.py
hdf5tools/cf.py
hdf5tools/combine.py
hdf5tools/core.py
hdf5tools/indexers.py
hdf5tools/utils.py
hdf5tools/tests/__init__.py
hdf5tools/tests/create_test_data.py
hdf5tools/tests/test_hdf5tools.py
hdf5tools-0.4.6.dist-info/METADATA
hdf5tools-0.4.6.dist-info/WHEEL
hdf5tools-0.4.6.dist-info/licenses/LICENSE
hdf5tools-0.4.6.dist-info/RECORD
