Metadata-Version: 2.4
Name: hdf5tools
Version: 0.4.6
Summary: Python hdf5 tools
Project-URL: Homepage, https://github.com/mullenkamp/hdf5tools
Author-email: Mike Kittridge <mullenkamp1@gmail.com>
License-Expression: Apache-2.0
License-File: LICENSE
Keywords: tethys
Classifier: Development Status :: 3 - Alpha
Classifier: Intended Audience :: Developers
Classifier: License :: OSI Approved :: Apache Software License
Classifier: Programming Language :: Python :: 3.8
Classifier: Programming Language :: Python :: 3.9
Classifier: Topic :: Scientific/Engineering :: Hydrology
Requires-Dist: cftime
Requires-Dist: h5py>=3.6.0
Requires-Dist: hdf5plugin>=3.3.1
Requires-Dist: numpy<2
Requires-Dist: xarray>=2022.03.0
